{
  "scores": [
    {
      "id": 1731757819867,
      "username": "ouissal",
      "score": 5,
      "date": "2024-11-16T11:50:19.867Z"
    },
    {
      "id": 1731757819872,
      "username": "ouissal",
      "score": 5,
      "date": "2024-11-16T11:50:19.872Z"
    },
    {
      "id": 1731757848165,
      "username": "dalal",
      "score": 8,
      "date": "2024-11-16T11:50:48.165Z"
    },
    {
      "id": 1731757848170,
      "username": "dalal",
      "score": 8,
      "date": "2024-11-16T11:50:48.170Z"
    },
    {
      "id": 1731758050851,
      "username": "dalal",
      "score": 13,
      "date": "2024-11-16T11:54:10.851Z"
    },
    {
      "id": 1731758050859,
      "username": "dalal",
      "score": 13,
      "date": "2024-11-16T11:54:10.859Z"
    },
    {
      "id": 1731758250522,
      "username": "ouissal",
      "score": 4,
      "date": "2024-11-16T11:57:30.522Z"
    },
    {
      "id": 1731758250526,
      "username": "ouissal",
      "score": 4,
      "date": "2024-11-16T11:57:30.526Z"
    },
    {
      "id": 1731758317012,
      "username": "youssef",
      "score": 6,
      "date": "2024-11-16T11:58:37.012Z"
    },
    {
      "id": 1731758317020,
      "username": "youssef",
      "score": 6,
      "date": "2024-11-16T11:58:37.020Z"
    },
    {
      "id": 1731758402339,
      "username": "dalal",
      "score": 7,
      "date": "2024-11-16T12:00:02.339Z"
    },
    {
      "id": 1731758402343,
      "username": "dalal",
      "score": 7,
      "date": "2024-11-16T12:00:02.343Z"
    }
  ]
}